Metadata-Version: 1.0
Name: dada-serde
Version: 0.0.9
Summary: (De)serialization utilities for dada-lake
Home-page: http://globally.ltd
Author: gltd
Author-email: hey@gltd.email
License: UNKNOWN
Platform: UNKNOWN
